paipline/Paip.py
paipline/__init__.py
paipline_zkchong-0.0.1.dist-info/LICENSE
paipline_zkchong-0.0.1.dist-info/METADATA
paipline_zkchong-0.0.1.dist-info/WHEEL
paipline_zkchong-0.0.1.dist-info/top_level.txt
paipline_zkchong-0.0.1.dist-info/RECORD
