Metadata-Version: 2.1
Name: paipline-zkchong
Version: 0.0.1
Summary: Simple pipeline alternative to Scikit Learn's Pipeline.
Home-page: https://github.com/zkchong/Paip
Author: Zan-Kai Chong
Author-email: zkchong@gmail.com
License: UNKNOWN
Platform: UNKNOWN
Classifier: Programming Language :: Python :: 3
Classifier: License :: OSI Approved :: GNU General Public License v3 (GPLv3)
Requires-Python: >=3.0
